smiths_svg/SmithsSvg.py
smiths_svg/__init__.py
smiths_svg/_imports_.py
smiths_svg/async-SmithsSvg.js
smiths_svg/async-SmithsSvg.js.map
smiths_svg/metadata.json
smiths_svg/package-info.json
smiths_svg/smiths_svg.min.js
smiths_svg/smiths_svg.min.js.map
smiths_svg-0.0.3.dist-info/LICENSE
smiths_svg-0.0.3.dist-info/METADATA
smiths_svg-0.0.3.dist-info/WHEEL
smiths_svg-0.0.3.dist-info/top_level.txt
smiths_svg-0.0.3.dist-info/RECORD
