Metadata-Version: 2.1
Name: smiths_svg
Version: 0.0.3
Summary: Project Description
Author: Rafael Sapere <rafael@jendamark.co.za>
Classifier: Framework :: Dash
License-File: LICENSE
